<?xml version="1.0" encoding="utf-8"?>
<!DOCTYPE module SYSTEM "../messages.dtd">
<messages>
    
    <message id="sponsor_navlabel">Sponsor</message>
    <message id="sponsor_contractduraction_info">Wählen Sie einen Sponsorvertrag bis zum Saisonende aus. Sie können Angebote verhandeln, aber bei zu hohem Risiko kann der Sponsor abspringen.</message>
    <message id="sponsor_no_offers">Im Moment ist kein Unternehmen an einem Sponsoring interessiert.</message>
    
    <message id="sponsor_choose_tooearly">Sie können erst ab dem %d. Spieltag einen neuen Sponsor auswählen.</message>
    
    <message id="sponsor_choose_novalidsponsor">Der ausgewählte Sponsor möchte doch nicht mehr mit Ihnen zusammenarbeiten. Ein anderes Team war vermutlich schneller oder das Angebot ist nicht mehr gültig.</message>
    <message id="sponsor_choose_stillcontract">Sie haben noch einen Vertrag mit einem Sponsor. Dieser läuft bis zum Saisonende.</message>
    <message id="sponsor_choose_success">Glückwunsch, Sie haben nun einen neuen Sponsor!</message>
    
    <message id="sponsor_championship_bonus_subject">Sponsorenprämie für gewonnene Meisterschaft</message>
    <message id="sponsor_cup_bonus_subject">Sponsorenprämie für Pokalrunde</message>

    <message id="sponsor_offer_type">Vertragstyp</message>
    <message id="sponsor_offer_type_safe">Sicher</message>
    <message id="sponsor_offer_type_risky">Risikoreich</message>
    <message id="sponsor_offer_type_fan">Fanbasiert</message>
    <message id="sponsor_offer_type_cup">Pokal</message>
    <message id="sponsor_offer_type_legacy">Alter Vertrag</message>

    <message id="sponsor_offer_description_safe">Hohe feste Zahlung, dafür geringere Erfolgsprämien.</message>
    <message id="sponsor_offer_description_risky">Niedrige feste Zahlung, dafür hohe Sieg- und Titelprämien.</message>
    <message id="sponsor_offer_description_fan">Zusatzbonus abhängig von der Stadionauslastung bei Heimspielen.</message>
    <message id="sponsor_offer_description_cup">Stärkerer Fokus auf Pokalspiele und erreichte Pokalrunden.</message>

    <message id="sponsor_attendance_bonus_percent">Zuschauerbonus</message>
    <message id="sponsor_contract_duration">Laufzeit</message>
    <message id="sponsor_contract_duration_season">bis Saisonende</message>
    <message id="sponsor_negotiate_button">Verhandeln</message>
    <message id="sponsor_negotiation_level">Verhandlungsstufe %d</message>
    <message id="sponsor_withdraw_chance">Absprungrisiko bei weiterer Verhandlung: %d %%</message>
    <message id="sponsor_negotiation_success">Die Verhandlung war erfolgreich. Das Angebot wurde verbessert.</message>
    <message id="sponsor_negotiation_withdrawn">Der Sponsor ist abgesprungen. Dieses Angebot steht nicht mehr zur Verfügung.</message>
    
</messages>
